pnote/__init__.py
pnote/__main__.py
pnote/layout.py
pnote/metadata.py
pnote/project.py
pnote/tools/__init__.py
pnote/tools/admin.py
pnote/tools/export.py
pnote/tools/search.py
pnote/tools/tag.py
pnote/tools/tool.py
pnote-0.0.27.dist-info/METADATA
pnote-0.0.27.dist-info/WHEEL
pnote-0.0.27.dist-info/entry_points.txt
pnote-0.0.27.dist-info/top_level.txt
pnote-0.0.27.dist-info/RECORD
