Metadata-Version: 2.1
Name: pnote
Version: 0.0.27
Summary: Simple note management tool
Requires-Dist: jsonschema
